idempotency_key/__init__.py
idempotency_key/decorators.py
idempotency_key/encoders.py
idempotency_key/exceptions.py
idempotency_key/locks/__init__.py
idempotency_key/locks/basic.py
idempotency_key/locks/redis.py
idempotency_key/middleware.py
idempotency_key/status.py
idempotency_key/storage.py
idempotency_key/utils.py
django_idempotency_key-1.2.0.dist-info/LICENSE
django_idempotency_key-1.2.0.dist-info/WHEEL
django_idempotency_key-1.2.0.dist-info/METADATA
django_idempotency_key-1.2.0.dist-info/RECORD
