Metadata-Version: 2.1
Name: django-idempotency-key
Version: 1.2.0
Summary: Django middleware for idempotency key support in view and viewset functions.
License: MIT
Author: YoyoDevs
Author-email: dev@yoyowallet.com
Requires-Python: >=3.7,<4
Classifier: License :: OSI Approved :: MIT License
Classifier: Programming Language :: Python :: 3
Classifier: Programming Language :: Python :: 3.10
Classifier: Programming Language :: Python :: 3.7
Classifier: Programming Language :: Python :: 3.8
Classifier: Programming Language :: Python :: 3.9
Requires-Dist: Django (>=2.2)
Requires-Dist: djangorestframework (>=3.8)
